scheduler/__init__.py
scheduler/admin.py
scheduler/models.py
scheduler/serializers.py
scheduler/tasks.py
scheduler/tests.py
scheduler/urls.py
scheduler/views.py
scheduler/management/__init__.py
scheduler/management/commands/__init__.py
scheduler/management/commands/trigger_deliver_tasks.py
scheduler/management/commands/trigger_periodic_task.py
scheduler/migrations/0001_initial.py
scheduler/migrations/0002_auto_20161012_2010.py
scheduler/migrations/0003_queuetaskrun.py
scheduler/migrations/0004_schedulefailure.py
scheduler/migrations/0005_auto_20181219_0934.py
scheduler/migrations/0006_schedule_last_run.py
scheduler/migrations/__init__.py
scheduler/templatetags/__init__.py
scheduler/templatetags/seed.py
seed_scheduler/__init__.py
seed_scheduler/celery.py
seed_scheduler/decorators.py
seed_scheduler/settings.py
seed_scheduler/test_decorators.py
seed_scheduler/testsettings.py
seed_scheduler/urls.py
seed_scheduler/utils.py
seed_scheduler/wsgi.py
seed_scheduler-0.10.3.dist-info/LICENCE
seed_scheduler-0.10.3.dist-info/METADATA
seed_scheduler-0.10.3.dist-info/WHEEL
seed_scheduler-0.10.3.dist-info/top_level.txt
seed_scheduler-0.10.3.dist-info/RECORD
